	<acaction acaction_id="@StoreEventSearchFormView" action="StoreEventSearchFormView"/>
	<acaction acaction_id="@StoreEventSearchResultView" action="StoreEventSearchResultView"/>
	<acactgrp acactgrp_id="@ConsumerDirectAllUsersViews" groupname="&STORE_IDENTIFIER;AllUsersViews" member_id="-2001"/>
	<acactactgp acactgrp_id="@ConsumerDirectAllUsersViews" acaction_id="@StoreEventSearchFormView"/>
	<acactactgp acactgrp_id="@ConsumerDirectAllUsersViews" acaction_id="@StoreEventSearchResultView"/>


	<acpolicy acpolicy_id="@acpolicy_id_1" policyname="AllUsersExecute&STORE_IDENTIFIER;AllUsersViews" member_id="@seller_b2c_mbr_id" mbrgrp_id="@-2001@AllUsers" acactgrp_id="@ConsumerDirectAllUsersViews" acresgrp_id="@ViewCommandResourceGroup" policytype="2"/>

	<acpolgrp acpolgrp_id="@acpolgrp_id_1" name="&STORE_IDENTIFIER; PolicyGroup" member_id="@seller_b2c_mbr_id"/>
	<acpolgppol acpolgrp_id="@acpolgrp_id_1" acpolicy_id="@acpolicy_id_1"/>
	<acplgpsubs acpolgrp_id="@acpolgrp_id_1" orgentity_id="@seller_b2c_orgentity_id"/>
	
	<acpolgrp acpolgrp_id="@ManagementAndAdministrationPolicyGroup@-2001" name="ManagementAndAdministrationPolicyGroup" member_id="-2001"/>
	<acplgpsubs acpolgrp_id="@ManagementAndAdministrationPolicyGroup@-2001" orgentity_id="@seller_b2c_orgentity_id"/>
	
	<acpolgrp acpolgrp_id="@CommonShoppingPolicyGroup@-2001" name="CommonShoppingPolicyGroup" member_id="-2001"/>
	<acplgpsubs acpolgrp_id="@CommonShoppingPolicyGroup@-2001" orgentity_id="@seller_b2c_orgentity_id"/>
	
	<acpolgrp acpolgrp_id="@B2CPolicyGroup@-2001" name="B2CPolicyGroup" member_id="-2001"/>
	<acplgpsubs acpolgrp_id="@B2CPolicyGroup@-2001" orgentity_id="@seller_b2c_orgentity_id"/>
